google/cloud/chronicle/__init__.py
google/cloud/chronicle/gapic_version.py
google/cloud/chronicle/py.typed
google/cloud/chronicle_v1/__init__.py
google/cloud/chronicle_v1/gapic_metadata.json
google/cloud/chronicle_v1/gapic_version.py
google/cloud/chronicle_v1/py.typed
google/cloud/chronicle_v1/services/__init__.py
google/cloud/chronicle_v1/services/data_access_control_service/__init__.py
google/cloud/chronicle_v1/services/data_access_control_service/async_client.py
google/cloud/chronicle_v1/services/data_access_control_service/client.py
google/cloud/chronicle_v1/services/data_access_control_service/pagers.py
google/cloud/chronicle_v1/services/data_access_control_service/transports/__init__.py
google/cloud/chronicle_v1/services/data_access_control_service/transports/base.py
google/cloud/chronicle_v1/services/data_access_control_service/transports/grpc.py
google/cloud/chronicle_v1/services/data_access_control_service/transports/grpc_asyncio.py
google/cloud/chronicle_v1/services/data_access_control_service/transports/rest.py
google/cloud/chronicle_v1/services/data_access_control_service/transports/rest_base.py
google/cloud/chronicle_v1/services/entity_service/__init__.py
google/cloud/chronicle_v1/services/entity_service/async_client.py
google/cloud/chronicle_v1/services/entity_service/client.py
google/cloud/chronicle_v1/services/entity_service/pagers.py
google/cloud/chronicle_v1/services/entity_service/transports/__init__.py
google/cloud/chronicle_v1/services/entity_service/transports/base.py
google/cloud/chronicle_v1/services/entity_service/transports/grpc.py
google/cloud/chronicle_v1/services/entity_service/transports/grpc_asyncio.py
google/cloud/chronicle_v1/services/entity_service/transports/rest.py
google/cloud/chronicle_v1/services/entity_service/transports/rest_base.py
google/cloud/chronicle_v1/services/instance_service/__init__.py
google/cloud/chronicle_v1/services/instance_service/async_client.py
google/cloud/chronicle_v1/services/instance_service/client.py
google_cloud_chronicle-0.3.0.dist-info/licenses/LICENSE
google_cloud_chronicle-0.3.0.dist-info/METADATA
google_cloud_chronicle-0.3.0.dist-info/WHEEL
google_cloud_chronicle-0.3.0.dist-info/top_level.txt
google_cloud_chronicle-0.3.0.dist-info/RECORD
